{
  "parent": "customitemsmod:customitems/limestone_block",
  "display": {
    "icon": {
      "id": "customitemsmod:magic_block"
    },
    "title": {
      "text": "Something Magical"
    },
    "description": {
      "text": "Learn a block that may do some magic"
    },
    "show_toast": true,
    "announce_to_chat": true,
    "hidden": false
  },
  "criteria": {
    "has_limestone": {
      "trigger": "minecraft:inventory_changed",
      "conditions": {
        "items": [
          {
            "items": "customitemsmod:limestone_block"
          }
        ]
      }
    }
  },
  "rewards": {
    "recipes": [
      "customitemsmod:magic_block"
    ]
  }
}